{
    "href":                       "",
    "title":                      "",
    "raw_hl_content":             "",
    "word_seg_processed_content": "",
    "keywords":                   [""],
    "hashtags":                   [""],
    "genre":                      "",
    "published_at":               "",
    "published_at_unix":          0,
    "author_href":                "",
    "author_name":                "",
    "series_href":                "",
    "series_name":                "",
    "series_num":                 0
    "reading_time":               0
}
